blockchain_utils/__init__.py
blockchain_utils/addresses.py
blockchain_utils/address_validators/__init__.py
blockchain_utils/address_validators/flow.py
blockchain_utils/address_validators/polkadot.py
blockchain_utils/address_validators/stellar.py
blockchain_utils-0.1.1.dist-info/METADATA
blockchain_utils-0.1.1.dist-info/WHEEL
blockchain_utils-0.1.1.dist-info/top_level.txt
blockchain_utils-0.1.1.dist-info/RECORD
